pycgtool/__init__.py
pycgtool/__main__.py
pycgtool/bondset.py
pycgtool/data/martini_v2.2.itp
pycgtool/data/w.itp
pycgtool/data/water.gro
pycgtool/data/watermodels.dat
pycgtool/forcefield.py
pycgtool/frame.py
pycgtool/functionalforms.py
pycgtool/mapping.py
pycgtool/parsers/__init__.py
pycgtool/parsers/cfg.py
pycgtool/parsers/itp.py
pycgtool/util.py
pycgtool-2.0.0.dist-info/entry_points.txt
pycgtool-2.0.0.dist-info/LICENSE
pycgtool-2.0.0.dist-info/WHEEL
pycgtool-2.0.0.dist-info/METADATA
pycgtool-2.0.0.dist-info/RECORD
