Metadata-Version: 2.1
Name: pycgtool
Version: 2.0.0
Summary: Generate coarse-grained molecular dynamics models from atomistic trajectories.
Home-page: https://github.com/jag1g13/pycgtool
License: GPL-3.0-only
Keywords: molecular-dynamics
Author: James Graham
Author-email: j.graham@soton.ac.uk
Requires-Python: >=3.6.2,<4.0.0
Classifier: Development Status :: 4 - Beta
Classifier: Environment :: Console
Classifier: Intended Audience :: Science/Research
Classifier: License :: OSI Approved :: GNU General Public License v3 (GPLv3)
Classifier: Programming Language :: Python :: 3
Classifier: Programming Language :: Python :: 3.7
Classifier: Programming Language :: Python :: 3.8
Classifier: Programming Language :: Python :: 3.9
Classifier: Topic :: Scientific/Engineering :: Chemistry
Provides-Extra: backmapping
Provides-Extra: docs
Requires-Dist: Sphinx (>=3.4.3,<4.0.0); extra == "docs"
Requires-Dist: astunparse (==1.6.2)
Requires-Dist: cowsay (>=4.0,<5.0)
Requires-Dist: mdplus (>=0.0.5,<0.0.6); extra == "backmapping"
Requires-Dist: mdtraj (>=1.9.5,<2.0.0,!=1.9.6)
Requires-Dist: myst-parser (>=0.13.5,<0.14.0); extra == "docs"
Requires-Dist: numpy (>=1.19.1,<2.0.0); python_version < "3.7"
Requires-Dist: numpy (>=1.20.0,<2.0.0); python_version >= "3.7"
Requires-Dist: rich (>=9.2.0,<10.0.0)
Requires-Dist: sphinx-autoapi (>=1.5.1,<2.0.0); extra == "docs"
Requires-Dist: sphinx-rtd-theme (>=0.5.1,<0.6.0); extra == "docs"
Requires-Dist: wheel (>=0.35.1,<0.36.0)
Project-URL: Documentation, https://pycgtool.readthedocs.io/en/main/
Project-URL: Repository, https://github.com/jag1g13/pycgtool
